odoo/addons/account_payment_mode_brand/README.rst
odoo/addons/account_payment_mode_brand/__init__.py
odoo/addons/account_payment_mode_brand/__manifest__.py
odoo/addons/account_payment_mode_brand/i18n/account_payment_mode_brand.pot
odoo/addons/account_payment_mode_brand/models/__init__.py
odoo/addons/account_payment_mode_brand/models/res_brand.py
odoo/addons/account_payment_mode_brand/models/res_brand_mixin.py
odoo/addons/account_payment_mode_brand/readme/CONTRIBUTORS.rst
odoo/addons/account_payment_mode_brand/readme/DESCRIPTION.rst
odoo/addons/account_payment_mode_brand/readme/USAGE.rst
odoo/addons/account_payment_mode_brand/static/description/icon.png
odoo/addons/account_payment_mode_brand/static/description/index.html
odoo/addons/account_payment_mode_brand/tests/__init__.py
odoo/addons/account_payment_mode_brand/tests/test_account_payment_mode_brand.py
odoo/addons/account_payment_mode_brand/views/account_invoice.xml
odoo/addons/account_payment_mode_brand/views/res_brand.xml
odoo12_addon_account_payment_mode_brand-12.0.1.0.0.99.dev5.dist-info/METADATA
odoo12_addon_account_payment_mode_brand-12.0.1.0.0.99.dev5.dist-info/WHEEL
odoo12_addon_account_payment_mode_brand-12.0.1.0.0.99.dev5.dist-info/top_level.txt
odoo12_addon_account_payment_mode_brand-12.0.1.0.0.99.dev5.dist-info/RECORD
