Metadata-Version: 2.1
Name: odoo12-addon-account-payment-mode-brand
Version: 12.0.1.0.0.99.dev5
Summary: This addon define allowed payment mode per brand
Home-page: https://github.com/OCA/brand
Author: ACSONE SA/NV,Odoo Community Association (OCA)
Author-email: support@odoo-community.org
License: AGPL-3
Platform: UNKNOWN
Classifier: Programming Language :: Python
Classifier: Framework :: Odoo
Classifier: Framework :: Odoo :: 12.0
Classifier: License :: OSI Approved :: GNU Affero General Public License v3
Requires-Python: >=3.5
Requires-Dist: odoo12-addon-account-brand
Requires-Dist: odoo12-addon-account-payment-partner
Requires-Dist: odoo12-addon-brand
Requires-Dist: odoo <12.1dev,>=12.0a
